nanogpt/__init__.py
nanogpt/auth.py
nanogpt/client.py
nanogpt/errors.py
nanogpt/endpoints/__init__.py
nanogpt/endpoints/chat.py
nanogpt/endpoints/images.py
nanogpt/endpoints/models.py
nanogpt/endpoints/videos.py
nanogpt_sdk-0.1.1.dist-info/licenses/LICENSE
nanogpt_sdk-0.1.1.dist-info/METADATA
nanogpt_sdk-0.1.1.dist-info/WHEEL
nanogpt_sdk-0.1.1.dist-info/top_level.txt
nanogpt_sdk-0.1.1.dist-info/RECORD
