Metadata-Version: 2.4
Name: nanogpt-sdk
Version: 0.1.1
Summary: Python client for the NanoGPT API
Author: Kalen McMillan
License: MIT
Project-URL: Homepage, https://github.com/kalenmcmillan/nanogpt-sdk
Project-URL: Repository, https://github.com/kalenmcmillan/nanogpt-sdk
Project-URL: Issues, https://github.com/kalenmcmillan/nanogpt-sdk/issues
Requires-Python: >=3.9
License-File: LICENSE
Requires-Dist: requests>=2.32.0
Dynamic: license-file
